bulbeewipy/__init__.py
bulbeewipy-1.0.4.dist-info/LICENSE
bulbeewipy-1.0.4.dist-info/METADATA
bulbeewipy-1.0.4.dist-info/WHEEL
bulbeewipy-1.0.4.dist-info/top_level.txt
bulbeewipy-1.0.4.dist-info/RECORD
