Metadata-Version: 2.1
Name: bulbeewipy
Version: 1.0.4
Summary: Python library to control Beewi SmartLight by Otio bulb in BLE
Home-page: https://github.com/bbo76/bulbeewipy
Author: bbo76
Author-email: baptiste.boquain@gmail.com
License: MIT
Keywords: beewi light ble homeassistant bluetooth otio
Platform: UNKNOWN
Classifier: Programming Language :: Python :: 3
Classifier: License :: OSI Approved :: MIT License
Classifier: Operating System :: OS Independent
Requires-Python: >=3.5
License-File: LICENSE
Requires-Dist: bluepy
Requires-Dist: tenacity
